setup.cfg
setup.py
pyjex/__init__.py
pyjex.egg-info/PKG-INFO
pyjex.egg-info/SOURCES.txt
pyjex.egg-info/dependency_links.txt
pyjex.egg-info/top_level.txt