Metadata-Version: 1.1
Name: pyjex
Version: 1.0.0
Summary: Java formatting for Python exceptions
Home-page: https://github.com/pierlauro/pyjex
Author: pierlauro
Author-email: sciarellip+pyjex@gmail.com
License: Public Domain
Keywords: exceptions stacktrace formatting
Platform: UNKNOWN
Classifier: Development Status :: 5 - Production/Stable
Classifier: Intended Audience :: Developers
Classifier: Programming Language :: Python :: 2
Classifier: Programming Language :: Python :: 2.7
Classifier: Programming Language :: Python :: 3
Classifier: Programming Language :: Python :: 3.4
Classifier: Programming Language :: Python :: 3.5
Classifier: Programming Language :: Python :: 3.6
